LICENSE
project47a/__init__.py
project47a/data/__init__.py
project47a/data/de.py
project47a-0.2.0.dist-info/LICENSE
project47a-0.2.0.dist-info/METADATA
project47a-0.2.0.dist-info/WHEEL
project47a-0.2.0.dist-info/RECORD
