Metadata-Version: 2.1
Name: project47a
Version: 0.2.0
Summary: Code name generator
Home-page: https://github.com/henryk/project47a
License: Apache-2.0
Author: Henryk Plötz
Author-email: henryk@ploetzli.ch
Requires-Python: >=3.9,<4.0
Classifier: Environment :: Console
Classifier: License :: OSI Approved :: Apache Software License
Classifier: Operating System :: OS Independent
Classifier: Programming Language :: Python :: 3
Classifier: Programming Language :: Python :: 3.9
Classifier: Programming Language :: Python :: 3.10
Classifier: Programming Language :: Python :: 3.11
Project-URL: Repository, https://github.com/henryk/project47a
